stsci/imagestats/__init__.py
stsci/imagestats/_version.py
stsci/imagestats/buildHistogram.cp314t-win32.pyd
stsci/imagestats/computeMean.cp314t-win32.pyd
stsci/imagestats/histogram1d.py
stsci/imagestats/tests/__init__.py
stsci/imagestats/tests/conftest.py
stsci/imagestats/tests/test_histogram1d.py
stsci/imagestats/tests/test_imagestats.py
stsci_imagestats-1.8.4.dist-info/licenses/LICENSE.txt
stsci_imagestats-1.8.4.dist-info/METADATA
stsci_imagestats-1.8.4.dist-info/WHEEL
stsci_imagestats-1.8.4.dist-info/top_level.txt
stsci_imagestats-1.8.4.dist-info/RECORD
