Metadata-Version: 2.4
Name: stsci.imagestats
Version: 1.8.4
Summary: Compute sigma-clipped statistics on data arrays
Author: Warren Hack, Christopher Hanley
Project-URL: Homepage, https://github.com/spacetelescope/stsci.imagestats
Project-URL: Tracker, https://github.com/spacetelescope/stsci.imagestats/issues
Project-URL: Documentation, https://stsciimagestats.readthedocs.io/en/stable/
Project-URL: Source Code, https://github.com/spacetelescope/stsci.imagestats
Classifier: Intended Audience :: Science/Research
Classifier: Operating System :: OS Independent
Classifier: Programming Language :: C
Classifier: Programming Language :: Cython
Classifier: Programming Language :: Python :: 3
Classifier: Programming Language :: Python :: Implementation :: CPython
Classifier: Topic :: Scientific/Engineering :: Astronomy
Classifier: Topic :: Scientific/Engineering :: Physics
Classifier: Development Status :: 7 - Inactive
Requires-Python: >=3.9
License-File: LICENSE.txt
Requires-Dist: numpy>=1.22
Provides-Extra: docs
Requires-Dist: numpydoc; extra == "docs"
Requires-Dist: sphinx; extra == "docs"
Requires-Dist: sphinx-automodapi; extra == "docs"
Requires-Dist: sphinx-rtd-theme; extra == "docs"
Requires-Dist: graphviz; extra == "docs"
Requires-Dist: tomli; python_version < "3.11" and extra == "docs"
Provides-Extra: test
Requires-Dist: pytest>=6.0; extra == "test"
Dynamic: license-file
